levee/__init__.py
levee/chart.py
levee/condition.py
levee/effect.py
levee/exceptions.py
levee/expressions.py
levee/state.py
levee-1.0.0.dist-info/licenses/LICENSE
levee-1.0.0.dist-info/METADATA
levee-1.0.0.dist-info/WHEEL
levee-1.0.0.dist-info/top_level.txt
levee-1.0.0.dist-info/RECORD
