Metadata-Version: 2.4
Name: levee
Version: 1.0.0
Summary: Create state machines with a visually pleasing syntax
Author-email: Gavin Ferise <gmferise@gmail.com>
License-Expression: Apache-2.0
Project-URL: Homepage, https://github.com/gmferise/levee
Project-URL: Issues, https://github.com/gmferise/levee/issues
Keywords: state,machine,machines,state machine,state machines,transition,transitions,flow,chart,flow chart,flow charts
Classifier: Programming Language :: Python :: 3
Classifier: Operating System :: OS Independent
Requires-Python: >=3.9
License-File: LICENSE
Dynamic: license-file
